pdstemplate/__init__.py
pdstemplate/_pdsblock.py
pdstemplate/_version.py
pdstemplate/asciitable.py
pdstemplate/pds3_syntax_checker.py
pdstemplate/pds3table.py
pdstemplate/utils.py
programs/__init__.py
programs/quicklabel.py
programs/tablelabel.py
rms_pdstemplate-2.4.0.dist-info/licenses/LICENSE
rms_pdstemplate-2.4.0.dist-info/METADATA
rms_pdstemplate-2.4.0.dist-info/WHEEL
rms_pdstemplate-2.4.0.dist-info/entry_points.txt
rms_pdstemplate-2.4.0.dist-info/top_level.txt
rms_pdstemplate-2.4.0.dist-info/RECORD
