Metadata-Version: 2.4
Name: rms-pdstemplate
Version: 2.4.0
Summary: Class to generate PDS labels based on templates
Maintainer-email: "Robert S. French" <rfrench@seti.org>
License: Apache-2.0
Project-URL: Homepage, https://github.com/SETI/rms-pdstemplate
Project-URL: Documentation, https://rms-pdstemplate.readthedocs.io/en/latest
Project-URL: Repository, https://github.com/SETI/rms-pdstemplate
Project-URL: Source, https://github.com/SETI/rms-pdstemplate
Project-URL: Issues, https://github.com/SETI/rms-pdstemplate/issues
Keywords: pdstemplate
Classifier: Development Status :: 5 - Production/Stable
Classifier: Natural Language :: English
Classifier: Topic :: Scientific/Engineering
Classifier: Topic :: Scientific/Engineering :: Astronomy
Classifier: License :: OSI Approved :: Apache Software License
Classifier: Programming Language :: Python :: 3.10
Classifier: Programming Language :: Python :: 3.11
Classifier: Programming Language :: Python :: 3.12
Classifier: Programming Language :: Python :: 3.13
Classifier: Operating System :: MacOS :: MacOS X
Classifier: Operating System :: POSIX :: Linux
Classifier: Operating System :: Microsoft :: Windows
Requires-Python: >=3.10
License-File: LICENSE
Requires-Dist: rms-filecache
Requires-Dist: rms-julian
Requires-Dist: rms-pdslogger
Requires-Dist: rms-pdsparser
Dynamic: license-file
